odoo/addons/mail_disable_follower_notification/README.rst
odoo/addons/mail_disable_follower_notification/__init__.py
odoo/addons/mail_disable_follower_notification/__manifest__.py
odoo/addons/mail_disable_follower_notification/i18n/it.po
odoo/addons/mail_disable_follower_notification/i18n/mail_disable_follower_notification.pot
odoo/addons/mail_disable_follower_notification/readme/CONTRIBUTORS.md
odoo/addons/mail_disable_follower_notification/readme/DESCRIPTION.md
odoo/addons/mail_disable_follower_notification/readme/USAGE.md
odoo/addons/mail_disable_follower_notification/static/description/icon.png
odoo/addons/mail_disable_follower_notification/static/description/icon.svg
odoo/addons/mail_disable_follower_notification/static/description/index.html
odoo/addons/mail_disable_follower_notification/wizards/__init__.py
odoo/addons/mail_disable_follower_notification/wizards/mail_wizard_invite.py
odoo_addon_mail_disable_follower_notification-17.0.1.0.0.4.dist-info/METADATA
odoo_addon_mail_disable_follower_notification-17.0.1.0.0.4.dist-info/WHEEL
odoo_addon_mail_disable_follower_notification-17.0.1.0.0.4.dist-info/top_level.txt
odoo_addon_mail_disable_follower_notification-17.0.1.0.0.4.dist-info/RECORD
